{"settings":{"gravityY":500,"countdown":0,"theme":0,"prizes":"34,38,45"},"layers":[[{"className":"frg.game.editor.objects::GroundPather","params":{"direction":90,"x":-100,"width":14455,"y":400,"height":2525,"shape":false,"lineId":0,"physic":false,"wireframe":false,"snapToGrid":false,"isRoad":false,"textureOffset":0,"repeatTexture":true,"smoothing":true,"straightSides":true,"vertices":[{"y":-8,"x":-3},{"y":-7,"x":1631},{"y":92,"x":1690},{"y":107,"x":1734},{"y":107,"x":1873},{"y":86,"x":1922},{"y":51,"x":1976},{"y":26,"x":2034},{"y":11,"x":2099},{"y":8,"x":2235},{"y":20,"x":2507},{"y":3,"x":2678},{"y":-11,"x":2774},{"y":-37,"x":2857},{"y":-77,"x":2923},{"y":-118,"x":2965},{"y":-168,"x":2995},{"y":-220,"x":3023},{"y":-248,"x":3042},{"y":-262,"x":3071},{"y":-260,"x":3120},{"y":-239,"x":3151},{"y":-183,"x":3182},{"y":-127,"x":3216},{"y":-95,"x":3254},{"y":-77,"x":3299},{"y":-80,"x":3358},{"y":-95,"x":3410},{"y":-123,"x":3451},{"y":-144,"x":3482},{"y":-162,"x":3516},{"y":-171,"x":3549},{"y":-173,"x":3580},{"y":-162,"x":3607},{"y":-149,"x":3628},{"y":-132,"x":3649},{"y":-102,"x":3672},{"y":-63,"x":3696},{"y":147,"x":3815},{"y":213,"x":3861},{"y":277,"x":3921},{"y":358,"x":4021},{"y":429,"x":4139},{"y":463,"x":4221},{"y":495,"x":4347},{"y":506,"x":4467},{"y":504,"x":4584},{"y":541,"x":4843},{"y":555,"x":4990},{"y":554,"x":5142},{"y":535,"x":5283},{"y":479,"x":5362},{"y":415,"x":5419},{"y":317,"x":5466},{"y":257,"x":5504},{"y":210,"x":5572},{"y":161,"x":5657},{"y":132,"x":5746},{"y":130,"x":5823},{"y":137,"x":5912},{"y":150,"x":5990},{"y":177,"x":6070},{"y":261,"x":6328},{"y":332,"x":6606},{"y":361,"x":6788},{"y":375,"x":6870},{"y":381,"x":6940},{"y":380,"x":7000},{"y":368,"x":7064},{"y":348,"x":7130},{"y":318,"x":7192},{"y":273,"x":7252},{"y":231,"x":7298},{"y":180,"x":7342},{"y":126,"x":7376},{"y":68,"x":7402},{"y":8,"x":7419},{"y":-15,"x":7443},{"y":-28,"x":7477},{"y":-33,"x":7524},{"y":-29,"x":7575},{"y":-14,"x":7628},{"y":19,"x":7661},{"y":96,"x":7707},{"y":144,"x":7753},{"y":182,"x":7823},{"y":212,"x":7905},{"y":246,"x":8006},{"y":272,"x":8094},{"y":301,"x":8208},{"y":314,"x":8301},{"y":315,"x":8403},{"y":315,"x":8525},{"y":308,"x":8703},{"y":281,"x":8837},{"y":234,"x":8972},{"y":192,"x":9097},{"y":135,"x":9232},{"y":75,"x":9359},{"y":9,"x":9454},{"y":-73,"x":9533},{"y":-130,"x":9593},{"y":-171,"x":9652},{"y":-193,"x":9720},{"y":-194,"x":9806},{"y":-183,"x":9949},{"y":-149,"x":10078},{"y":753,"x":11755},{"y":788,"x":11851},{"y":805,"x":11940},{"y":808,"x":12028},{"y":802,"x":12107},{"y":783,"x":12189},{"y":754,"x":12261},{"y":718,"x":12327},{"y":675,"x":12383},{"y":615,"x":12447},{"y":554,"x":12496},{"y":540,"x":12562},{"y":542,"x":12651},{"y":566,"x":12736},{"y":603,"x":12788},{"y":679,"x":12852},{"y":698,"x":12899},{"y":699,"x":12992},{"y":698,"x":13101},{"y":698,"x":13227},{"y":656,"x":13348},{"y":-43,"x":14434},{"y":-1704,"x":14439}],"line":false,"thick":128,"stretchTexture":false,"directed":false,"originOffsetRatio":0,"camera":true,"cameraOffsetY":120,"textureMode":true,"rotation":0}},{"className":"frg.game.editor.objects::LandscapeShaper","params":{"x":14339,"graphic":true,"ignore":false,"y":-1312,"physic":false,"safeId":-1,"vertices":[{"y":0,"x":0},{"y":5,"x":1220},{"y":2750,"x":1215},{"y":2745,"x":-5}],"layer":2,"isWheel":false,"density":1,"isStatic":true,"plr":false,"line":false,"rotation":0,"id":-1,"rem":true}},{"className":"frg.game.editor.objects::PillarPather","params":{"straightSides":true,"x":13390,"width":511.9,"y":210,"repeatTexture":true,"stretchTexture":false,"vertices":[{"y":408,"x":486},{"y":-4,"x":0},{"y":615,"x":216}],"originOffsetRatio":0,"height":653.75,"wireframe":false,"type":2,"snapToGrid":true,"textureMode":true,"textureOffset":0,"rotation":0,"smoothing":true}},{"className":"FinishZone","params":{"x":12960,"width":397,"y":1120,"rotation":0,"height":308}},{"className":"frg.game.editor.objects::PillarPather","params":{"straightSides":true,"x":7719,"width":1159.05,"y":4,"repeatTexture":true,"stretchTexture":false,"vertices":[{"y":585,"x":3},{"y":15,"x":2},{"y":66,"x":49},{"y":113,"x":104},{"y":157,"x":159},{"y":209,"x":236},{"y":249,"x":322},{"y":277,"x":418},{"y":297,"x":518},{"y":303,"x":615},{"y":298,"x":716},{"y":278,"x":828},{"y":248,"x":932},{"y":212,"x":1016},{"y":164,"x":1095},{"y":128,"x":1143},{"y":630,"x":1143}],"originOffsetRatio":0,"height":644.6,"wireframe":false,"type":2,"snapToGrid":false,"textureMode":true,"textureOffset":0,"rotation":0,"smoothing":true}},{"className":"frg.game.editor.objects::LandscapeShaper","params":{"x":7670,"graphic":true,"ignore":true,"y":50,"physic":true,"safeId":1,"vertices":[{"y":-85,"x":35},{"y":-90,"x":50},{"y":-85,"x":65},{"y":-60,"x":80},{"y":16,"x":70},{"y":41,"x":81},{"y":56,"x":98},{"y":68,"x":122},{"y":72,"x":162},{"y":90,"x":185},{"y":105,"x":130},{"y":90,"x":47},{"y":110,"x":-35},{"y":90,"x":-80},{"y":74,"x":-53},{"y":68,"x":-13},{"y":55,"x":10},{"y":38,"x":21},{"y":13,"x":29},{"y":-60,"x":20}],"layer":5,"isWheel":false,"density":1,"isStatic":false,"plr":false,"line":false,"rotation":0,"id":-1,"rem":true}},{"className":"frg.game.editor.objects::LandscapeShaper","params":{"x":4900,"graphic":true,"ignore":false,"y":447,"physic":true,"safeId":-1,"vertices":[{"y":0,"x":0},{"y":-11,"x":23},{"y":-18,"x":52},{"y":-19,"x":85},{"y":-10,"x":119},{"y":5,"x":147},{"y":26,"x":169},{"y":54,"x":189},{"y":88,"x":199},{"y":114,"x":201},{"y":140,"x":199},{"y":168,"x":189},{"y":193,"x":174},{"y":213,"x":155},{"y":228,"x":134},{"y":239,"x":109},{"y":244,"x":79},{"y":244,"x":53},{"y":236,"x":21},{"y":223,"x":-4},{"y":206,"x":-23},{"y":184,"x":-42},{"y":161,"x":-55},{"y":132,"x":-61},{"y":99,"x":-61},{"y":69,"x":-54},{"y":41,"x":-41},{"y":17,"x":-21}],"layer":3,"isWheel":false,"density":1,"isStatic":false,"plr":false,"line":false,"rotation":0,"id":-1,"rem":true}},{"className":"frg.game.editor.objects::LandscapeShaper","params":{"x":4730,"graphic":true,"ignore":false,"y":847,"physic":true,"safeId":-1,"vertices":[{"y":0,"x":0},{"y":-11,"x":23},{"y":-18,"x":52},{"y":-19,"x":85},{"y":-10,"x":119},{"y":5,"x":147},{"y":26,"x":169},{"y":54,"x":189},{"y":88,"x":199},{"y":114,"x":201},{"y":140,"x":199},{"y":168,"x":189},{"y":193,"x":174},{"y":213,"x":155},{"y":228,"x":134},{"y":239,"x":109},{"y":244,"x":79},{"y":244,"x":53},{"y":236,"x":21},{"y":223,"x":-4},{"y":206,"x":-23},{"y":184,"x":-42},{"y":161,"x":-55},{"y":132,"x":-61},{"y":99,"x":-61},{"y":69,"x":-54},{"y":41,"x":-41},{"y":17,"x":-21}],"layer":3,"isWheel":false,"density":1,"isStatic":false,"plr":false,"line":false,"rotation":0,"id":-1,"rem":true}},{"className":"frg.game.editor.objects::LandscapeShaper","params":{"x":5059,"graphic":true,"ignore":false,"y":857,"physic":true,"safeId":-1,"vertices":[{"y":0,"x":0},{"y":-11,"x":23},{"y":-18,"x":52},{"y":-19,"x":85},{"y":-10,"x":119},{"y":5,"x":147},{"y":26,"x":169},{"y":54,"x":189},{"y":88,"x":199},{"y":114,"x":201},{"y":140,"x":199},{"y":168,"x":189},{"y":193,"x":174},{"y":213,"x":155},{"y":228,"x":134},{"y":239,"x":109},{"y":244,"x":79},{"y":244,"x":53},{"y":236,"x":21},{"y":223,"x":-4},{"y":206,"x":-23},{"y":184,"x":-42},{"y":161,"x":-55},{"y":132,"x":-61},{"y":99,"x":-61},{"y":69,"x":-54},{"y":41,"x":-41},{"y":17,"x":-21}],"layer":3,"isWheel":false,"density":1,"isStatic":false,"plr":false,"line":false,"rotation":0,"id":-1,"rem":true}},{"className":"frg.game.editor.objects::LandscapeShaper","params":{"x":4921,"graphic":true,"ignore":false,"y":712,"physic":true,"safeId":-1,"vertices":[{"y":0,"x":0},{"y":-10,"x":25},{"y":-12,"x":49},{"y":-7,"x":76},{"y":4,"x":100},{"y":23,"x":122},{"y":47,"x":137},{"y":74,"x":142},{"y":102,"x":142},{"y":129,"x":132},{"y":153,"x":112},{"y":170,"x":89},{"y":179,"x":63},{"y":178,"x":31},{"y":169,"x":2},{"y":155,"x":-17},{"y":139,"x":-31},{"y":116,"x":-43},{"y":86,"x":-48},{"y":59,"x":-44},{"y":35,"x":-36},{"y":17,"x":-20}],"layer":3,"isWheel":false,"density":1,"isStatic":false,"plr":false,"line":false,"rotation":0,"id":-1,"rem":true}},{"className":"frg.game.editor.objects::PillarPather","params":{"straightSides":true,"x":4860,"width":342.95,"y":1110,"repeatTexture":true,"stretchTexture":false,"vertices":[{"y":0,"x":0},{"y":-147,"x":-58},{"y":-310,"x":107},{"y":-138,"x":264},{"y":0,"x":210}],"originOffsetRatio":0,"height":329.5,"wireframe":false,"type":2,"snapToGrid":true,"textureMode":true,"textureOffset":0,"rotation":0,"smoothing":true}},{"className":"frg.game.editor.objects::PillarPather","params":{"straightSides":true,"x":4922,"width":459.65,"y":560,"repeatTexture":true,"stretchTexture":false,"vertices":[{"y":537,"x":-182},{"y":0,"x":48},{"y":552,"x":261}],"originOffsetRatio":0,"height":582.35,"wireframe":false,"type":2,"snapToGrid":true,"textureMode":true,"textureOffset":0,"rotation":0,"smoothing":true}},{"className":"frg.game.editor.objects::PillarPather","params":{"straightSides":true,"x":4790,"width":185.1,"y":560,"repeatTexture":true,"stretchTexture":false,"vertices":[{"y":-55,"x":8},{"y":470,"x":-160}],"originOffsetRatio":0,"height":538,"wireframe":false,"type":2,"snapToGrid":true,"textureMode":true,"textureOffset":0,"rotation":0,"smoothing":true}},{"className":"frg.game.editor.objects::LandscapeShaper","params":{"x":13385,"graphic":true,"ignore":false,"y":109,"physic":true,"safeId":2,"vertices":[{"y":30,"x":-22},{"y":-16,"x":-4},{"y":-57,"x":18},{"y":-100,"x":57},{"y":-133,"x":110},{"y":-149,"x":160},{"y":-156,"x":213},{"y":-150,"x":259},{"y":-133,"x":314},{"y":-103,"x":364},{"y":-63,"x":400},{"y":-16,"x":427},{"y":41,"x":445},{"y":78,"x":448},{"y":89,"x":422},{"y":24,"x":389},{"y":-30,"x":349},{"y":-62,"x":314},{"y":-83,"x":274},{"y":-95,"x":234},{"y":-93,"x":191},{"y":-83,"x":146},{"y":-62,"x":106},{"y":-37,"x":80},{"y":-1,"x":52},{"y":36,"x":37},{"y":97,"x":35},{"y":100,"x":0},{"y":70,"x":-30}],"layer":4,"isWheel":false,"density":1,"isStatic":false,"plr":false,"line":false,"rotation":0,"id":-1,"rem":true}},{"className":"frg.game.editor.objects::PillarPather","params":{"straightSides":true,"x":4810,"width":75.7,"y":520,"repeatTexture":true,"stretchTexture":false,"vertices":[{"y":-15,"x":-8},{"y":290,"x":50}],"originOffsetRatio":0,"height":318,"wireframe":false,"type":2,"snapToGrid":true,"textureMode":true,"textureOffset":0,"rotation":0,"smoothing":true}},{"className":"frg.game.editor.objects::GroundPather","params":{"direction":90,"x":-100,"width":14482.5,"y":400,"height":2552.55,"shape":true,"lineId":0,"physic":true,"wireframe":false,"snapToGrid":false,"isRoad":true,"textureOffset":0,"repeatTexture":true,"smoothing":true,"straightSides":true,"vertices":[{"y":-8,"x":-3},{"y":-7,"x":1631},{"y":1,"x":1640},{"y":-1,"x":1650},{"y":86,"x":1696},{"y":87,"x":1707},{"y":107,"x":1734},{"y":107,"x":1873},{"y":86,"x":1901},{"y":85,"x":1915},{"y":-1,"x":1956},{"y":0,"x":1970},{"y":-8,"x":1974},{"y":-14,"x":2024},{"y":-22,"x":2067},{"y":-18,"x":2100},{"y":-12,"x":2141},{"y":-5,"x":2181},{"y":-8,"x":2214},{"y":-2,"x":2254},{"y":1,"x":2298},{"y":-8,"x":2340},{"y":0,"x":2385},{"y":13,"x":2433},{"y":6,"x":2488},{"y":6,"x":2552},{"y":-5,"x":2606},{"y":-15,"x":2658},{"y":-6,"x":2713},{"y":-11,"x":2774},{"y":-37,"x":2857},{"y":-77,"x":2923},{"y":-118,"x":2965},{"y":-168,"x":2995},{"y":-220,"x":3023},{"y":-248,"x":3042},{"y":-262,"x":3071},{"y":-260,"x":3120},{"y":-239,"x":3151},{"y":-183,"x":3182},{"y":-127,"x":3216},{"y":-95,"x":3254},{"y":-77,"x":3299},{"y":-80,"x":3358},{"y":-95,"x":3410},{"y":-123,"x":3451},{"y":-144,"x":3482},{"y":-162,"x":3516},{"y":-171,"x":3549},{"y":-173,"x":3580},{"y":-162,"x":3607},{"y":-149,"x":3628},{"y":-132,"x":3649},{"y":-102,"x":3672},{"y":-63,"x":3696},{"y":147,"x":3815},{"y":213,"x":3861},{"y":277,"x":3921},{"y":358,"x":4021},{"y":429,"x":4139},{"y":463,"x":4221},{"y":495,"x":4347},{"y":506,"x":4467},{"y":504,"x":4584},{"y":585,"x":4633},{"y":590,"x":4682},{"y":617,"x":4685},{"y":619,"x":4742},{"y":672,"x":4804},{"y":698,"x":4870},{"y":702,"x":4929},{"y":680,"x":5005},{"y":675,"x":5059},{"y":678,"x":5102},{"y":691,"x":5154},{"y":709,"x":5215},{"y":705,"x":5270},{"y":690,"x":5305},{"y":669,"x":5328},{"y":610,"x":5375},{"y":512,"x":5406},{"y":412,"x":5426},{"y":317,"x":5466},{"y":257,"x":5504},{"y":210,"x":5572},{"y":161,"x":5657},{"y":132,"x":5746},{"y":130,"x":5823},{"y":137,"x":5912},{"y":150,"x":5990},{"y":177,"x":6070},{"y":261,"x":6328},{"y":332,"x":6606},{"y":361,"x":6788},{"y":375,"x":6870},{"y":381,"x":6940},{"y":380,"x":7000},{"y":368,"x":7064},{"y":348,"x":7130},{"y":318,"x":7192},{"y":273,"x":7252},{"y":231,"x":7298},{"y":180,"x":7342},{"y":126,"x":7376},{"y":68,"x":7402},{"y":8,"x":7419},{"y":-15,"x":7443},{"y":-28,"x":7477},{"y":-33,"x":7524},{"y":-29,"x":7575},{"y":-14,"x":7628},{"y":19,"x":7661},{"y":96,"x":7707},{"y":144,"x":7753},{"y":182,"x":7823},{"y":212,"x":7905},{"y":246,"x":8006},{"y":272,"x":8094},{"y":301,"x":8208},{"y":314,"x":8301},{"y":315,"x":8403},{"y":315,"x":8525},{"y":308,"x":8703},{"y":281,"x":8837},{"y":234,"x":8972},{"y":192,"x":9097},{"y":135,"x":9232},{"y":75,"x":9359},{"y":9,"x":9454},{"y":-73,"x":9533},{"y":-130,"x":9593},{"y":-171,"x":9652},{"y":-193,"x":9720},{"y":-194,"x":9806},{"y":-183,"x":9949},{"y":-149,"x":10078},{"y":753,"x":11755},{"y":788,"x":11851},{"y":805,"x":11940},{"y":808,"x":12028},{"y":802,"x":12107},{"y":783,"x":12189},{"y":754,"x":12261},{"y":718,"x":12327},{"y":675,"x":12383},{"y":615,"x":12447},{"y":554,"x":12496},{"y":540,"x":12562},{"y":542,"x":12651},{"y":566,"x":12736},{"y":603,"x":12788},{"y":679,"x":12852},{"y":698,"x":12899},{"y":699,"x":12992},{"y":698,"x":13101},{"y":698,"x":13227},{"y":719,"x":13241},{"y":656,"x":13348},{"y":-43,"x":14434},{"y":-1704,"x":14439}],"line":true,"thick":128,"stretchTexture":false,"directed":true,"originOffsetRatio":0,"camera":false,"cameraOffsetY":120,"textureMode":true,"rotation":0}},{"className":"frg.game.editor.objects::LandscapeShaper","params":{"x":7562,"graphic":true,"ignore":false,"y":112,"physic":true,"safeId":1,"vertices":[{"y":1,"x":2},{"y":2,"x":18},{"y":10,"x":40},{"y":15,"x":71},{"y":18,"x":109},{"y":20,"x":151},{"y":19,"x":190},{"y":15,"x":236},{"y":9,"x":278},{"y":-5,"x":310},{"y":-5,"x":330},{"y":10,"x":340},{"y":35,"x":335},{"y":54,"x":324},{"y":67,"x":303},{"y":74,"x":254},{"y":79,"x":203},{"y":81,"x":151},{"y":77,"x":91},{"y":71,"x":40},{"y":62,"x":6},{"y":52,"x":-4},{"y":34,"x":-8},{"y":13,"x":-5}],"layer":4,"isWheel":false,"density":1,"isStatic":false,"plr":false,"line":false,"rotation":0,"id":-1,"rem":true}},{"className":"frg.game.editor.objects::LandscapeShaper","params":{"x":4492,"graphic":true,"ignore":false,"y":901,"physic":true,"safeId":-1,"vertices":[{"y":0,"x":0},{"y":-15,"x":56},{"y":-39,"x":108},{"y":-75,"x":155},{"y":-121,"x":202},{"y":-165,"x":234},{"y":-224,"x":264},{"y":-292,"x":280},{"y":-348,"x":282},{"y":-394,"x":280},{"y":-416,"x":291},{"y":-416,"x":312},{"y":-411,"x":331},{"y":-372,"x":333},{"y":-308,"x":331},{"y":-250,"x":324},{"y":-193,"x":307},{"y":-135,"x":277},{"y":-95,"x":251},{"y":-54,"x":213},{"y":-21,"x":172},{"y":5,"x":131},{"y":30,"x":80},{"y":33,"x":49},{"y":27,"x":25}],"layer":4,"isWheel":false,"density":1,"isStatic":false,"plr":false,"line":false,"rotation":0,"id":-1,"rem":true}},{"className":"frg.game.editor.objects::LandscapeShaper","params":{"x":8013,"graphic":true,"ignore":false,"y":-603,"physic":true,"safeId":1,"vertices":[{"y":0,"x":0},{"y":-38,"x":57},{"y":-72,"x":120},{"y":-94,"x":192},{"y":-106,"x":269},{"y":-104,"x":344},{"y":-95,"x":415},{"y":-77,"x":480},{"y":-50,"x":537},{"y":-9,"x":598},{"y":38,"x":651},{"y":98,"x":701},{"y":167,"x":743},{"y":257,"x":775},{"y":335,"x":785},{"y":405,"x":786},{"y":486,"x":774},{"y":566,"x":748},{"y":641,"x":706},{"y":707,"x":651},{"y":768,"x":580},{"y":814,"x":502},{"y":839,"x":428},{"y":854,"x":342},{"y":850,"x":254},{"y":837,"x":166},{"y":801,"x":87},{"y":753,"x":9},{"y":687,"x":-60},{"y":601,"x":-120},{"y":520,"x":-155},{"y":411,"x":-173},{"y":351,"x":-175},{"y":295,"x":-169},{"y":232,"x":-155},{"y":158,"x":-125},{"y":103,"x":-93},{"y":55,"x":-54}],"layer":3,"isWheel":false,"density":1,"isStatic":false,"plr":false,"line":false,"rotation":0,"id":-1,"rem":true}},{"className":"frg.game.editor.objects::LandscapeShaper","params":{"x":7461,"graphic":true,"ignore":false,"y":192,"physic":true,"safeId":1,"vertices":[{"y":0,"x":0},{"y":-10,"x":25},{"y":-12,"x":49},{"y":-7,"x":76},{"y":4,"x":100},{"y":23,"x":122},{"y":47,"x":137},{"y":74,"x":142},{"y":102,"x":142},{"y":129,"x":132},{"y":153,"x":112},{"y":170,"x":89},{"y":179,"x":63},{"y":178,"x":31},{"y":169,"x":2},{"y":155,"x":-17},{"y":139,"x":-31},{"y":116,"x":-43},{"y":86,"x":-48},{"y":59,"x":-44},{"y":35,"x":-36},{"y":17,"x":-20}],"layer":3,"isWheel":false,"density":1,"isStatic":false,"plr":false,"line":false,"rotation":0,"id":-1,"rem":true}},{"className":"frg.game.editor.objects::LandscapeShaper","params":{"x":7675,"graphic":true,"ignore":false,"y":374,"physic":true,"safeId":1,"vertices":[{"y":0,"x":0},{"y":-10,"x":25},{"y":-12,"x":49},{"y":-7,"x":76},{"y":4,"x":100},{"y":23,"x":122},{"y":47,"x":137},{"y":74,"x":142},{"y":102,"x":142},{"y":129,"x":132},{"y":153,"x":112},{"y":170,"x":89},{"y":179,"x":63},{"y":178,"x":31},{"y":169,"x":2},{"y":155,"x":-17},{"y":139,"x":-31},{"y":116,"x":-43},{"y":86,"x":-48},{"y":59,"x":-44},{"y":35,"x":-36},{"y":17,"x":-20}],"layer":3,"isWheel":false,"density":1,"isStatic":false,"plr":false,"line":false,"rotation":0,"id":-1,"rem":true}},{"className":"frg.game.editor.objects::LandscapeShaper","params":{"x":7901,"graphic":true,"ignore":false,"y":458,"physic":true,"safeId":1,"vertices":[{"y":0,"x":0},{"y":-10,"x":25},{"y":-12,"x":49},{"y":-7,"x":76},{"y":4,"x":100},{"y":23,"x":122},{"y":47,"x":137},{"y":74,"x":142},{"y":102,"x":142},{"y":129,"x":132},{"y":153,"x":112},{"y":170,"x":89},{"y":179,"x":63},{"y":178,"x":31},{"y":169,"x":2},{"y":155,"x":-17},{"y":139,"x":-31},{"y":116,"x":-43},{"y":86,"x":-48},{"y":59,"x":-44},{"y":35,"x":-36},{"y":17,"x":-20}],"layer":3,"isWheel":false,"density":1,"isStatic":false,"plr":false,"line":false,"rotation":0,"id":-1,"rem":true}},{"className":"frg.game.editor.objects::LandscapeShaper","params":{"x":8371,"graphic":true,"ignore":false,"y":522,"physic":true,"safeId":1,"vertices":[{"y":0,"x":0},{"y":-10,"x":25},{"y":-12,"x":49},{"y":-7,"x":76},{"y":4,"x":100},{"y":23,"x":122},{"y":47,"x":137},{"y":74,"x":142},{"y":102,"x":142},{"y":129,"x":132},{"y":153,"x":112},{"y":170,"x":89},{"y":179,"x":63},{"y":178,"x":31},{"y":169,"x":2},{"y":155,"x":-17},{"y":139,"x":-31},{"y":116,"x":-43},{"y":86,"x":-48},{"y":59,"x":-44},{"y":35,"x":-36},{"y":17,"x":-20}],"layer":3,"isWheel":false,"density":1,"isStatic":false,"plr":false,"line":false,"rotation":0,"id":-1,"rem":true}},{"className":"frg.game.editor.objects::LandscapeShaper","params":{"x":8611,"graphic":true,"ignore":false,"y":502,"physic":true,"safeId":1,"vertices":[{"y":0,"x":0},{"y":-10,"x":25},{"y":-12,"x":49},{"y":-7,"x":76},{"y":4,"x":100},{"y":23,"x":122},{"y":47,"x":137},{"y":74,"x":142},{"y":102,"x":142},{"y":129,"x":132},{"y":153,"x":112},{"y":170,"x":89},{"y":179,"x":63},{"y":178,"x":31},{"y":169,"x":2},{"y":155,"x":-17},{"y":139,"x":-31},{"y":116,"x":-43},{"y":86,"x":-48},{"y":59,"x":-44},{"y":35,"x":-36},{"y":17,"x":-20}],"layer":3,"isWheel":false,"density":1,"isStatic":false,"plr":false,"line":false,"rotation":0,"id":-1,"rem":true}},{"className":"frg.game.editor.objects::LandscapeShaper","params":{"x":8821,"graphic":true,"ignore":false,"y":432,"physic":true,"safeId":1,"vertices":[{"y":0,"x":0},{"y":-10,"x":25},{"y":-12,"x":49},{"y":-7,"x":76},{"y":4,"x":100},{"y":23,"x":122},{"y":47,"x":137},{"y":74,"x":142},{"y":102,"x":142},{"y":129,"x":132},{"y":153,"x":112},{"y":170,"x":89},{"y":179,"x":63},{"y":178,"x":31},{"y":169,"x":2},{"y":155,"x":-17},{"y":139,"x":-31},{"y":116,"x":-43},{"y":86,"x":-48},{"y":59,"x":-44},{"y":35,"x":-36},{"y":17,"x":-20}],"layer":3,"isWheel":false,"density":1,"isStatic":false,"plr":false,"line":false,"rotation":0,"id":-1,"rem":true}},{"className":"frg.game.editor.objects::LandscapeShaper","params":{"x":8141,"graphic":true,"ignore":false,"y":512,"physic":true,"safeId":1,"vertices":[{"y":0,"x":0},{"y":-10,"x":25},{"y":-12,"x":49},{"y":-7,"x":76},{"y":4,"x":100},{"y":23,"x":122},{"y":47,"x":137},{"y":74,"x":142},{"y":102,"x":142},{"y":129,"x":132},{"y":153,"x":112},{"y":170,"x":89},{"y":179,"x":63},{"y":178,"x":31},{"y":169,"x":2},{"y":155,"x":-17},{"y":139,"x":-31},{"y":116,"x":-43},{"y":86,"x":-48},{"y":59,"x":-44},{"y":35,"x":-36},{"y":17,"x":-20}],"layer":3,"isWheel":false,"density":1,"isStatic":false,"plr":false,"line":false,"rotation":0,"id":-1,"rem":true}},{"className":"frg.game.editor.objects::LandscapeShaper","params":{"x":9031,"graphic":true,"ignore":false,"y":352,"physic":true,"safeId":1,"vertices":[{"y":0,"x":0},{"y":-10,"x":25},{"y":-12,"x":49},{"y":-7,"x":76},{"y":4,"x":100},{"y":23,"x":122},{"y":47,"x":137},{"y":74,"x":142},{"y":102,"x":142},{"y":129,"x":132},{"y":153,"x":112},{"y":170,"x":89},{"y":179,"x":63},{"y":178,"x":31},{"y":169,"x":2},{"y":155,"x":-17},{"y":139,"x":-31},{"y":116,"x":-43},{"y":86,"x":-48},{"y":59,"x":-44},{"y":35,"x":-36},{"y":17,"x":-20}],"layer":3,"isWheel":false,"density":1,"isStatic":false,"plr":false,"line":false,"rotation":0,"id":-1,"rem":true}},{"className":"frg.game.editor.objects::LandscapeShaper","params":{"x":9231,"graphic":true,"ignore":false,"y":232,"physic":true,"safeId":1,"vertices":[{"y":0,"x":0},{"y":-10,"x":25},{"y":-12,"x":49},{"y":-7,"x":76},{"y":4,"x":100},{"y":23,"x":122},{"y":47,"x":137},{"y":74,"x":142},{"y":102,"x":142},{"y":129,"x":132},{"y":153,"x":112},{"y":170,"x":89},{"y":179,"x":63},{"y":178,"x":31},{"y":169,"x":2},{"y":155,"x":-17},{"y":139,"x":-31},{"y":116,"x":-43},{"y":86,"x":-48},{"y":59,"x":-44},{"y":35,"x":-36},{"y":17,"x":-20}],"layer":3,"isWheel":false,"density":1,"isStatic":false,"plr":false,"line":false,"rotation":0,"id":-1,"rem":true}},{"className":"frg.game.editor.objects::LandscapeShaper","params":{"x":12760,"graphic":true,"ignore":false,"y":847,"physic":true,"safeId":2,"vertices":[{"y":0,"x":0},{"y":-11,"x":23},{"y":-18,"x":52},{"y":-19,"x":85},{"y":-10,"x":119},{"y":5,"x":147},{"y":26,"x":169},{"y":54,"x":189},{"y":88,"x":199},{"y":114,"x":201},{"y":140,"x":199},{"y":168,"x":189},{"y":193,"x":174},{"y":213,"x":155},{"y":228,"x":134},{"y":239,"x":109},{"y":244,"x":79},{"y":244,"x":53},{"y":236,"x":21},{"y":223,"x":-4},{"y":206,"x":-23},{"y":184,"x":-42},{"y":161,"x":-55},{"y":132,"x":-61},{"y":99,"x":-61},{"y":69,"x":-54},{"y":41,"x":-41},{"y":17,"x":-21}],"layer":3,"isWheel":false,"density":0.3,"isStatic":false,"plr":false,"line":false,"rotation":0,"id":-1,"rem":true}},{"className":"frg.game.editor.objects::LandscapeShaper","params":{"x":13020,"graphic":true,"ignore":false,"y":847,"physic":true,"safeId":2,"vertices":[{"y":0,"x":0},{"y":-11,"x":23},{"y":-18,"x":52},{"y":-19,"x":85},{"y":-10,"x":119},{"y":5,"x":147},{"y":26,"x":169},{"y":54,"x":189},{"y":88,"x":199},{"y":114,"x":201},{"y":140,"x":199},{"y":168,"x":189},{"y":193,"x":174},{"y":213,"x":155},{"y":228,"x":134},{"y":239,"x":109},{"y":244,"x":79},{"y":244,"x":53},{"y":236,"x":21},{"y":223,"x":-4},{"y":206,"x":-23},{"y":184,"x":-42},{"y":161,"x":-55},{"y":132,"x":-61},{"y":99,"x":-61},{"y":69,"x":-54},{"y":41,"x":-41},{"y":17,"x":-21}],"layer":3,"isWheel":false,"density":0.3,"isStatic":false,"plr":false,"line":false,"rotation":0,"id":-1,"rem":true}},{"className":"frg.game.editor.objects::LandscapeShaper","params":{"x":12735,"graphic":true,"ignore":false,"y":-180,"physic":true,"safeId":2,"vertices":[{"y":-825,"x":50},{"y":-825,"x":380},{"y":-155,"x":370},{"y":-150,"x":310},{"y":-135,"x":250},{"y":-116,"x":205},{"y":-93,"x":168},{"y":-63,"x":134},{"y":-30,"x":116},{"y":7,"x":102},{"y":47,"x":96},{"y":100,"x":100},{"y":98,"x":49}],"layer":4,"isWheel":false,"density":1,"isStatic":false,"plr":false,"line":false,"rotation":0,"id":-1,"rem":true}},{"className":"frg.game.editor.objects::PillarPather","params":{"straightSides":true,"x":7390,"width":2003,"y":370,"repeatTexture":true,"stretchTexture":false,"vertices":[{"y":0,"x":25},{"y":-93,"x":120},{"y":87,"x":333},{"y":168,"x":559},{"y":222,"x":800},{"y":231,"x":1029},{"y":211,"x":1269},{"y":143,"x":1479},{"y":64,"x":1689},{"y":-53,"x":1890},{"y":-14,"x":2015}],"originOffsetRatio":0,"height":345.15,"wireframe":false,"type":2,"snapToGrid":false,"textureMode":true,"textureOffset":0,"rotation":0,"smoothing":true}},{"className":"frg.game.editor.objects::LandscapeShaper","params":{"x":-40,"graphic":true,"ignore":false,"y":170,"physic":true,"safeId":-1,"vertices":[{"y":-285,"x":0},{"y":-285,"x":135},{"y":230,"x":135},{"y":230,"x":0}],"layer":0,"isWheel":false,"density":1,"isStatic":true,"plr":false,"line":false,"rotation":0,"id":-1,"rem":true}}],[{"className":"SignPillar","params":{"x":5810,"scaleY":1,"y":472,"height":128.35,"width":9.3,"rotation":0,"scaleX":1}},{"className":"SignPillar","params":{"x":9800,"scaleY":1,"y":148,"height":128.35,"width":9.3,"rotation":0,"scaleX":1}},{"className":"Sign2","params":{"x":7720,"width":70.65,"y":310,"rotation":0,"height":70.65}},{"className":"Dec13","params":{"x":580,"scaleY":1,"y":300,"height":213.45,"width":171.75,"rotation":0,"scaleX":1}},{"className":"Dec14","params":{"x":690,"scaleY":1,"y":290,"height":244.8,"width":165.85,"rotation":0,"scaleX":1}},{"className":"Dec13","params":{"x":200,"scaleY":1,"y":300,"height":213.45,"width":171.75,"rotation":0,"scaleX":1}},{"className":"Dec15","params":{"x":1290,"scaleY":1,"y":280,"height":234.2,"width":197,"rotation":0,"scaleX":1}},{"className":"Dec13","params":{"x":2130,"scaleY":1,"y":300,"height":213.45,"width":171.75,"rotation":0,"scaleX":1}},{"className":"Dec15","params":{"x":2720,"scaleY":1,"y":260,"height":234.2,"width":197,"rotation":-21,"scaleX":1}},{"className":"Dec14","params":{"x":3530,"scaleY":1,"y":120,"height":244.8,"width":165.85,"rotation":3,"scaleX":1}},{"className":"Dec14","params":{"x":3820,"scaleY":1,"y":480,"height":244.8,"width":165.85,"rotation":45,"scaleX":1}},{"className":"Dec13","params":{"x":4300,"scaleY":1,"y":790,"height":213.45,"width":171.75,"rotation":45,"scaleX":1}},{"className":"Dec15","params":{"x":5500,"scaleY":1,"y":480,"height":234.2,"width":197,"rotation":-15,"scaleX":1}},{"className":"Dec14","params":{"x":6460,"scaleY":1,"y":600,"height":244.8,"width":165.85,"rotation":6,"scaleX":1}},{"className":"Dec13","params":{"x":9510,"scaleY":1,"y":130,"height":213.45,"width":171.75,"rotation":0,"scaleX":1}},{"className":"Dec14","params":{"x":10480,"scaleY":1,"y":380,"height":244.8,"width":165.85,"rotation":18,"scaleX":1}},{"className":"Dec13","params":{"x":10340,"scaleY":1,"y":370,"height":213.45,"width":171.75,"rotation":3,"scaleX":1}},{"className":"Dec14","params":{"x":10900,"scaleY":1,"y":610,"height":244.8,"width":165.85,"rotation":15,"scaleX":1}},{"className":"Dec15","params":{"x":11380,"scaleY":1,"y":890,"height":234.2,"width":197,"rotation":18,"scaleX":1}},{"className":"Dec16","params":{"x":12470,"scaleY":1,"y":840,"height":242.2,"width":176.2,"rotation":0,"scaleX":1}}],[{"className":"Removed0","params":{"x":1568,"width":12.3,"y":380,"height":72,"safeId":-1,"rotation":60,"id":21,"active":false}},{"className":"Removed1","params":{"x":1601,"width":13.1,"y":462,"height":48.2,"safeId":-1,"rotation":0,"id":21,"active":false}},{"className":"Removed0","params":{"x":1634,"width":12.3,"y":357,"height":72,"safeId":-1,"rotation":81,"id":21,"active":false}},{"className":"Removed0","params":{"x":1704,"width":12.3,"y":352,"height":72,"safeId":-1,"rotation":90,"id":21,"active":false}},{"className":"Removed0","params":{"x":1774,"width":12.3,"y":358,"height":72,"safeId":-1,"rotation":99,"id":21,"active":false}},{"className":"Removed0","params":{"x":1840,"width":12.3,"y":380,"height":72,"safeId":-1,"rotation":117,"id":21,"active":false}},{"className":"Removed0","params":{"x":1669,"width":12.3,"y":392,"height":72,"safeId":-1,"rotation":0,"id":21,"active":false}},{"className":"Removed0","params":{"x":1739,"width":12.3,"y":392,"height":72,"safeId":-1,"rotation":0,"id":21,"active":false}},{"className":"Removed0","params":{"x":1669,"width":12.3,"y":432,"height":72,"safeId":-1,"rotation":90,"id":21,"active":false}},{"className":"Removed0","params":{"x":1739,"width":12.3,"y":432,"height":72,"safeId":-1,"rotation":90,"id":21,"active":false}},{"className":"Removed0","params":{"x":1639,"width":12.3,"y":472,"height":72,"safeId":-1,"rotation":0,"id":21,"active":false}},{"className":"Removed0","params":{"x":1704,"width":12.3,"y":472,"height":72,"safeId":-1,"rotation":0,"id":21,"active":false}},{"className":"Removed0","params":{"x":1769,"width":12.3,"y":472,"height":72,"safeId":-1,"rotation":0,"id":21,"active":false}},{"className":"Removed0","params":{"x":1602,"width":12.3,"y":421,"height":72,"safeId":-1,"rotation":90,"id":21,"active":false}},{"className":"Removed0","params":{"x":1807,"width":12.3,"y":451,"height":72,"safeId":-1,"rotation":0,"id":21,"active":false}},{"className":"Removed1","params":{"x":1807,"width":13.1,"y":393,"height":48.2,"safeId":-1,"rotation":0,"id":21,"active":false}},{"className":"Removed1","params":{"x":1601,"width":13.1,"y":392,"height":48.2,"safeId":-1,"rotation":0,"id":21,"active":false}},{"className":"Removed1","params":{"x":1601,"width":13.1,"y":432,"height":48.2,"safeId":-1,"rotation":90,"id":21,"active":false}},{"className":"BarrelE","params":{"x":3206,"width":53,"y":294,"height":53,"safeId":-1,"rotation":0,"id":-1,"active":true}},{"className":"Tnt1","params":{"x":3260,"count":40,"y":293,"height":53.2,"safeId":-1,"impulse":3000,"width":53.2,"radius":64,"physic":true,"rotation":0,"id":1,"stones":true}},{"className":"BarrelE","params":{"x":3226,"width":53,"y":244,"height":53,"safeId":-1,"rotation":0,"id":-1,"active":true}},{"className":"BarrelE","params":{"x":3156,"width":53,"y":264,"height":53,"safeId":-1,"rotation":0,"id":-1,"active":true}},{"className":"BarrelE","params":{"x":3176,"width":53,"y":214,"height":53,"safeId":-1,"rotation":0,"id":-1,"active":true}},{"className":"BarrelE","params":{"x":3126,"width":53,"y":214,"height":53,"safeId":-1,"rotation":0,"id":-1,"active":true}},{"className":"Tnt1","params":{"x":4560,"count":12,"y":960,"height":53.2,"safeId":-1,"impulse":0,"width":53.2,"radius":64,"physic":false,"rotation":0,"id":3,"stones":false}},{"className":"Tnt1","params":{"x":4615,"count":12,"y":940,"height":53.2,"safeId":-1,"impulse":0,"width":53.2,"radius":64,"physic":false,"rotation":0,"id":3,"stones":false}},{"className":"Tnt1","params":{"x":4615,"count":12,"y":990,"height":53.2,"safeId":-1,"impulse":0,"width":53.2,"radius":64,"physic":false,"rotation":0,"id":3,"stones":false}},{"className":"BarrelE","params":{"x":3096,"width":53,"y":164,"height":53,"safeId":-1,"rotation":0,"id":-1,"active":true}},{"className":"Tnt1","params":{"x":12960,"count":40,"y":1070,"height":53.2,"safeId":2,"impulse":10000,"width":53.2,"radius":64,"physic":true,"rotation":0,"id":11,"stones":false}},{"className":"SpikesE","params":{"x":13187,"width":125.3,"y":1071,"rotation":146.99999999999991,"height":46.9}},{"className":"SpikesE","params":{"x":13287,"width":125.3,"y":1007,"rotation":146.99999999999991,"height":46.9}},{"className":"SpikesE","params":{"x":13487,"width":125.3,"y":879,"rotation":146.99999999999991,"height":46.9}},{"className":"SpikesE","params":{"x":13387,"width":125.3,"y":943,"rotation":146.99999999999991,"height":46.9}},{"className":"SpikesE","params":{"x":13887,"width":125.3,"y":622,"rotation":146.99999999999991,"height":46.9}},{"className":"SpikesE","params":{"x":13787,"width":125.3,"y":686,"rotation":146.99999999999991,"height":46.9}},{"className":"SpikesE","params":{"x":13687,"width":125.3,"y":750,"rotation":146.99999999999991,"height":46.9}},{"className":"SpikesE","params":{"x":13587,"width":125.3,"y":814,"rotation":146.99999999999991,"height":46.9}},{"className":"SpikesE","params":{"x":14287,"width":125.3,"y":365,"rotation":146.99999999999991,"height":46.9}},{"className":"SpikesE","params":{"x":14187,"width":125.3,"y":429,"rotation":146.99999999999991,"height":46.9}},{"className":"SpikesE","params":{"x":14087,"width":125.3,"y":493,"rotation":146.99999999999991,"height":46.9}},{"className":"SpikesE","params":{"x":13987,"width":125.3,"y":557,"rotation":146.99999999999991,"height":46.9}},{"className":"SpikesE","params":{"x":14320,"width":125.3,"y":290,"rotation":90,"height":46.9}},{"className":"SpikesE","params":{"x":14320,"width":125.3,"y":170,"rotation":90,"height":46.9}},{"className":"SpikesE","params":{"x":14320,"width":125.3,"y":50,"rotation":90,"height":46.9}},{"className":"SpikesE","params":{"x":14320,"width":125.3,"y":-310,"rotation":90,"height":46.9}},{"className":"SpikesE","params":{"x":14320,"width":125.3,"y":-190,"rotation":90,"height":46.9}},{"className":"SpikesE","params":{"x":14320,"width":125.3,"y":-70,"rotation":90,"height":46.9}},{"className":"SpikesE","params":{"x":14320,"width":125.3,"y":-670,"rotation":90,"height":46.9}},{"className":"SpikesE","params":{"x":14320,"width":125.3,"y":-550,"rotation":90,"height":46.9}},{"className":"SpikesE","params":{"x":14320,"width":125.3,"y":-430,"rotation":90,"height":46.9}}],null,[{"className":"PlayerWP","params":{"x":450,"width":64,"y":320,"rotation":0,"height":32}},{"className":"SafePointE","params":{"x":5810,"width":128,"y":390,"height":2088,"rotation":0,"id":1}},{"className":"SafePointE","params":{"x":9800,"width":128,"y":70,"height":1900,"rotation":0,"id":2}}],[{"className":"ToggleE","params":{"x":3170,"width":64,"off":false,"y":10,"hint":-1,"height":1402,"safeId":-1,"id_off":-1,"sndId":-1,"rotation":0,"id":1}},{"className":"MotorJointE","params":{"x":4807,"graphic":1,"y":504,"height":17,"safeId":-1,"width":17,"rate":140,"time":0.45,"snd":false,"swoosh":false,"rotation":0,"id":3}},{"className":"PivotJointE","params":{"x":4520,"graphic":0,"y":910,"height":17,"safeId":-1,"width":17,"rotation":0,"id":3}},{"className":"MotorJointE","params":{"x":4970,"graphic":2,"y":560,"height":17,"safeId":-1,"width":17,"rate":180,"time":800,"snd":false,"swoosh":true,"rotation":0,"id":2}},{"className":"MotorJointE","params":{"x":5130,"graphic":2,"y":970,"height":17,"safeId":-1,"width":17,"rate":180,"time":800,"snd":false,"swoosh":true,"rotation":0,"id":2}},{"className":"MotorJointE","params":{"x":4800,"graphic":2,"y":960,"height":17,"safeId":-1,"width":17,"rate":180,"time":800,"snd":false,"swoosh":true,"rotation":0,"id":2}},{"className":"MotorJointE","params":{"x":4969,"graphic":2,"y":796,"height":17,"safeId":-1,"width":17,"rate":-180,"time":800,"snd":false,"swoosh":true,"rotation":0,"id":2}},{"className":"ToggleE","params":{"x":4170,"width":64,"off":false,"y":250,"hint":-1,"height":1547,"safeId":-1,"id_off":-1,"sndId":-1,"rotation":0,"id":2}},{"className":"ToggleE","params":{"x":4670,"width":449,"off":false,"y":280,"hint":-1,"height":64,"safeId":-1,"id_off":-1,"sndId":-1,"rotation":0,"id":3}},{"className":"frg.game.editor.objects::MoverPather","params":{"accelDist":100,"x":7722,"stopOnEnd":true,"startTime":"0","y":162,"height":305,"speed":200,"stopOnPoint":false,"vertices":[{"y":0,"x":0},{"y":70,"x":66},{"y":139,"x":149},{"y":204,"x":246},{"y":243,"x":335},{"y":269,"x":428},{"y":284,"x":517},{"y":292,"x":609},{"y":288,"x":709},{"y":270,"x":824},{"y":235,"x":942},{"y":182,"x":1055},{"y":111,"x":1155}],"active":0,"position":0,"sideWait":0,"width":1168,"cycle":0,"body":false,"safeId":1,"sideAngle":0,"snapToGrid":false,"rotation":0,"id":4}},{"className":"ToggleE","params":{"x":7728,"width":226,"off":false,"y":144,"hint":-1,"height":64,"safeId":1,"id_off":-1,"sndId":-1,"rotation":0,"id":4}},{"className":"frg.game.editor.objects::MoverPather","params":{"accelDist":100,"x":7722,"stopOnEnd":true,"startTime":"0","y":94,"height":305,"speed":200,"stopOnPoint":false,"vertices":[{"y":0,"x":0},{"y":70,"x":66},{"y":139,"x":149},{"y":204,"x":246},{"y":243,"x":335},{"y":269,"x":428},{"y":284,"x":517},{"y":292,"x":609},{"y":288,"x":709},{"y":270,"x":824},{"y":235,"x":942},{"y":182,"x":1055},{"y":111,"x":1155}],"active":0,"position":0,"sideWait":0,"width":1168,"cycle":0,"body":false,"safeId":1,"sideAngle":0,"snapToGrid":false,"rotation":0,"id":4}},{"className":"MotorJointE","params":{"x":8321,"graphic":0,"y":-229,"height":17,"safeId":1,"width":17,"rate":400,"time":800,"snd":false,"swoosh":false,"rotation":0,"id":8}},{"className":"ToggleE","params":{"x":7390,"width":64,"off":false,"y":-200,"hint":-1,"height":1472,"safeId":1,"id_off":-1,"sndId":-1,"rotation":0,"id":8}},{"className":"MotorJointE","params":{"x":7509,"graphic":2,"y":276,"height":17,"safeId":1,"width":17,"rate":180,"time":800,"snd":false,"swoosh":true,"rotation":0,"id":9}},{"className":"MotorJointE","params":{"x":7723,"graphic":2,"y":458,"height":17,"safeId":1,"width":17,"rate":180,"time":800,"snd":false,"swoosh":true,"rotation":0,"id":9}},{"className":"MotorJointE","params":{"x":7949,"graphic":2,"y":542,"height":17,"safeId":1,"width":17,"rate":180,"time":800,"snd":false,"swoosh":true,"rotation":0,"id":9}},{"className":"MotorJointE","params":{"x":8419,"graphic":2,"y":606,"height":17,"safeId":1,"width":17,"rate":180,"time":800,"snd":false,"swoosh":true,"rotation":0,"id":9}},{"className":"MotorJointE","params":{"x":8659,"graphic":2,"y":586,"height":17,"safeId":1,"width":17,"rate":180,"time":800,"snd":false,"swoosh":true,"rotation":0,"id":9}},{"className":"MotorJointE","params":{"x":8869,"graphic":2,"y":516,"height":17,"safeId":1,"width":17,"rate":180,"time":800,"snd":false,"swoosh":true,"rotation":0,"id":9}},{"className":"MotorJointE","params":{"x":8189,"graphic":2,"y":596,"height":17,"safeId":1,"width":17,"rate":180,"time":800,"snd":false,"swoosh":true,"rotation":0,"id":9}},{"className":"MotorJointE","params":{"x":9079,"graphic":2,"y":436,"height":17,"safeId":1,"width":17,"rate":180,"time":800,"snd":false,"swoosh":true,"rotation":0,"id":9}},{"className":"MotorJointE","params":{"x":9279,"graphic":2,"y":316,"height":17,"safeId":1,"width":17,"rate":180,"time":800,"snd":false,"swoosh":true,"rotation":0,"id":9}},{"className":"ToggleE","params":{"x":6620,"width":64,"off":false,"y":70,"hint":-1,"height":1472,"safeId":1,"id_off":-1,"sndId":-1,"rotation":0,"id":9}},{"className":"MotorJointE","params":{"x":13391,"graphic":2,"y":198,"height":17,"safeId":2,"width":17,"rate":400,"time":0.28,"snd":true,"swoosh":false,"rotation":0,"id":12}},{"className":"PivotJointE","params":{"x":13820,"graphic":0,"y":180,"height":17,"safeId":2,"width":17,"rotation":0,"id":12}},{"className":"ToggleE","params":{"x":12950,"width":64,"off":false,"y":620,"hint":-1,"height":568,"safeId":2,"id_off":-1,"sndId":-1,"rotation":0,"id":12}},{"className":"frg.game.editor.objects::MoverPather","params":{"accelDist":0,"x":12950,"stopOnEnd":true,"startTime":"0","y":-610,"height":445,"speed":800,"stopOnPoint":false,"vertices":[{"y":0,"x":0},{"y":432,"x":0}],"active":0,"position":0,"sideWait":0,"width":13,"cycle":0,"body":false,"safeId":2,"sideAngle":0,"snapToGrid":true,"rotation":0,"id":13}},{"className":"ToggleE","params":{"x":13430,"width":106,"off":false,"y":260,"hint":-1,"height":90,"safeId":2,"id_off":-1,"sndId":-1,"rotation":0,"id":13}},{"className":"ToggleE","params":{"x":12900,"width":64,"off":false,"y":10,"hint":-1,"height":568,"safeId":2,"id_off":-1,"sndId":-1,"rotation":0,"id":11}},{"className":"ToggleE","params":{"x":1450,"width":64,"off":false,"y":160,"hint":-1,"height":985,"safeId":-1,"id_off":-1,"sndId":-1,"rotation":0,"id":21}},{"className":"ToggleE","params":{"x":1860,"width":64,"off":false,"y":210,"hint":-1,"height":1120,"safeId":-1,"id_off":-1,"sndId":0,"rotation":0,"id":0}},{"className":"ToggleE","params":{"x":3600,"width":64,"off":false,"y":-60,"hint":-1,"height":1120,"safeId":-1,"id_off":-1,"sndId":0,"rotation":0,"id":0}},{"className":"ToggleE","params":{"x":8340,"width":64,"off":false,"y":290,"hint":-1,"height":1120,"safeId":1,"id_off":-1,"sndId":0,"rotation":0,"id":0}},{"className":"ToggleE","params":{"x":13110,"width":64,"off":false,"y":280,"hint":-1,"height":1120,"safeId":2,"id_off":-1,"sndId":0,"rotation":0,"id":0}}]]}